CHANGES.txt
MANIFEST.in
README.md
lstrike.py
requirements.txt
setup.cfg
setup.py
luckystrike/__init__.py
luckystrike/config.py
luckystrike/httpstream.py
luckystrike/route.py
luckystrike/stream.py
luckystrike/user.py
luckystrike/util.py
luckystrike.egg-info/PKG-INFO
luckystrike.egg-info/SOURCES.txt
luckystrike.egg-info/dependency_links.txt
luckystrike.egg-info/requires.txt
luckystrike.egg-info/top_level.txt