Metadata-Version: 1.1
Name: luckystrike
Version: 0.11
Summary: IRC to Campfire Bridge
Home-page: https://github.com/mmichie/luckystrike
Author: Matt Michie
Author-email: mmichie@gmail.com
License: The MIT License (MIT)
Download-URL: https://github.com/mmichie/luckystrike/tarball/0.11
Keywords: campfire,irc,bridge
Platform: UNKNOWN
Classifier: Topic :: Communications :: Chat :: Internet Relay Chat
Classifier: Programming Language :: Python :: 2.7
Classifier: License :: OSI Approved :: MIT License
